README
pefile.py
peutils.py
setup.cfg
setup.py
ordlookup/__init__.py
ordlookup/oleaut32.py
ordlookup/ws2_32.py
pefile2.egg-info/PKG-INFO
pefile2.egg-info/SOURCES.txt
pefile2.egg-info/dependency_links.txt
pefile2.egg-info/top_level.txt