Metadata-Version: 1.1
Name: pefile2
Version: 1.2.11
Summary: Python PE parsing module
Home-page: http://code.google.com/p/pefile/
Author: Ero Carrera
Author-email: ero.carrera@gmail.com
License: UNKNOWN
Download-URL: http://pefile.googlecode.com/files/pefile-1.2.11.tar.gz
Platform: any
Classifier: Development Status :: 5 - Production/Stable
Classifier: Intended Audience :: Developers
Classifier: Intended Audience :: Science/Research
Classifier: Natural Language :: English
Classifier: Operating System :: OS Independent
Classifier: Programming Language :: Python
Classifier: Topic :: Software Development :: Libraries :: Python Modules
